zeptum/__init__.py
zeptum/core.py
zaptum-1.0.0.dist-info/METADATA
zaptum-1.0.0.dist-info/WHEEL
zaptum-1.0.0.dist-info/top_level.txt
zaptum-1.0.0.dist-info/RECORD
